TrieCLI/__init__.py
TrieCLI/app.py
TrieCLI/server.py
TrieCLI/trie.py
TrieCLI/trie1.py
TrieCLI/visualize.py
TrieCLI-0.0.2.dist-info/LICENSE.txt
TrieCLI-0.0.2.dist-info/METADATA
TrieCLI-0.0.2.dist-info/WHEEL
TrieCLI-0.0.2.dist-info/top_level.txt
TrieCLI-0.0.2.dist-info/RECORD
