Metadata-Version: 2.1
Name: TrieCLI
Version: 0.0.2
Summary: A command line interface implmenting the trie data structure
Home-page: https://github.com/NNDEV1/TrieCLI
Author: Nalin Nagar
Author-email: nalinnagar1@gmail.com
License: UNKNOWN
Platform: UNKNOWN
Classifier: Programming Language :: Python :: 3
Classifier: License :: OSI Approved :: MIT License
Classifier: Operating System :: OS Independent
Requires-Python: >=3.2
License-File: LICENSE.txt
Requires-Dist: requests
Requires-Dist: flask
Requires-Dist: pyfiglet
